qemu/qmp/__init__.py
qemu/qmp/error.py
qemu/qmp/events.py
qemu/qmp/legacy.py
qemu/qmp/message.py
qemu/qmp/models.py
qemu/qmp/protocol.py
qemu/qmp/py.typed
qemu/qmp/qmp_client.py
qemu/qmp/qmp_shell.py
qemu/qmp/qmp_tui.py
qemu/qmp/util.py
qemu_qmp-0.0.4.dist-info/LICENSE
qemu_qmp-0.0.4.dist-info/LICENSE_GPL2
qemu_qmp-0.0.4.dist-info/METADATA
qemu_qmp-0.0.4.dist-info/WHEEL
qemu_qmp-0.0.4.dist-info/entry_points.txt
qemu_qmp-0.0.4.dist-info/top_level.txt
qemu_qmp-0.0.4.dist-info/RECORD
