Metadata-Version: 2.2
Name: qemu.qmp
Version: 0.0.4
Summary: QEMU Monitor Protocol library
Home-page: https://gitlab.com/qemu-project/python-qemu-qmp
Author: QEMU Project
Author-email: qemu-devel@nongnu.org
Maintainer: John Snow
Maintainer-email: jsnow@redhat.com
Project-URL: Homepage, https://www.qemu.org/
Project-URL: Documentation, https://qemu.readthedocs.io/projects/python-qemu-qmp/en/latest/
Project-URL: Changelog, https://qemu.readthedocs.io/projects/python-qemu-qmp/en/latest/main.html#changelog
Project-URL: Issues, https://gitlab.com/qemu-project/python-qemu-qmp/-/issues
Project-URL: Source, https://gitlab.com/qemu-project/python-qemu-qmp
Classifier: Development Status :: 3 - Alpha
Classifier: Intended Audience :: Developers
Classifier: License :: OSI Approved :: GNU Lesser General Public License v2 or later (LGPLv2+)
Classifier: License :: OSI Approved :: GNU General Public License v2 (GPLv2)
Classifier: Natural Language :: English
Classifier: Operating System :: OS Independent
Classifier: Programming Language :: Python :: 3 :: Only
Classifier: Programming Language :: Python :: 3.8
Classifier: Programming Language :: Python :: 3.9
Classifier: Programming Language :: Python :: 3.10
Classifier: Programming Language :: Python :: 3.11
Classifier: Programming Language :: Python :: 3.12
Classifier: Programming Language :: Python :: 3.13
Classifier: Programming Language :: Python :: 3.14
Classifier: Topic :: System :: Emulators
Classifier: Typing :: Typed
Requires-Python: >=3.8
License-File: LICENSE
License-File: LICENSE_GPL2
Provides-Extra: devel
Requires-Dist: pytest>=5.2.1; extra == "devel"
Requires-Dist: coverage>=6.1.0; extra == "devel"
Requires-Dist: flake8>=5.0.4; extra == "devel"
Requires-Dist: isort>=5.1.2; extra == "devel"
Requires-Dist: mypy>=1.4.0; extra == "devel"
Requires-Dist: pylint>=2.17.3; extra == "devel"
Requires-Dist: setuptools>=66.1.0; python_version >= "3.12" and extra == "devel"
Requires-Dist: tox>=3.18.0; extra == "devel"
Requires-Dist: urwid>=2.1.2; extra == "devel"
Requires-Dist: urwid-readline>=0.13; extra == "devel"
Requires-Dist: Pygments>=2.9.0; extra == "devel"
Provides-Extra: tui
Requires-Dist: urwid>=2.1.2; extra == "tui"
Requires-Dist: urwid-readline>=0.13; extra == "tui"
Requires-Dist: Pygments>=2.9.0; extra == "tui"
Provides-Extra: build-docs
Requires-Dist: sphinx>=5.3.0; extra == "build-docs"
Requires-Dist: sphinx_rtd_theme>=1.1.1; extra == "build-docs"
Requires-Dist: setuptools_scm>=8.0.0; extra == "build-docs"
